xnldorker/__init__.py
xnldorker/xnldorker.py
xnldorker-4.0.dist-info/METADATA
xnldorker-4.0.dist-info/WHEEL
xnldorker-4.0.dist-info/entry_points.txt
xnldorker-4.0.dist-info/top_level.txt
xnldorker-4.0.dist-info/RECORD
