Metadata-Version: 2.4
Name: xnldorker
Version: 4.0
Summary: Run a dork on different search sites
Home-page: https://github.com/xnl-h4ck3r/xnldorker
Author: @xnl-h4ck3r
Requires-Dist: termcolor
Requires-Dist: requests
Requires-Dist: asyncio
Requires-Dist: beautifulsoup4
Requires-Dist: playwright
Requires-Dist: tldextract
Requires-Dist: urllib3
Dynamic: author
Dynamic: description
Dynamic: description-content-type
Dynamic: home-page
Dynamic: requires-dist
Dynamic: summary
